emailx/__init__.py
emailx/emailer.py
emailx/unicode.py
emailx-0.1.1510835164.dist-info/DESCRIPTION.rst
emailx-0.1.1510835164.dist-info/METADATA
emailx-0.1.1510835164.dist-info/RECORD
emailx-0.1.1510835164.dist-info/WHEEL
emailx-0.1.1510835164.dist-info/metadata.json
emailx-0.1.1510835164.dist-info/top_level.txt
tests/__init__.py
tests/test_all.py
