Metadata-Version: 2.0
Name: emailx
Version: 0.1.1510835164
Summary: easy as hell email sending for python
Home-page: https://github.com/djrobstep/emailx
Author: Robert Lechte
Author-email: robertlechte@gmail.com
License: UNKNOWN
Platform: UNKNOWN
Classifier: Development Status :: 4 - Beta
Classifier: Intended Audience :: Developers
Classifier: Natural Language :: English
Classifier: Programming Language :: Python
Classifier: Programming Language :: Python :: 2.7
Classifier: Programming Language :: Python :: 3
Classifier: Programming Language :: Python :: 3.6
Classifier: Programming Language :: Python :: Implementation :: CPython
Requires-Dist: six
